[
	{
		"key": "sb",
		"value": "nifmZsCEm1Wh5AfDjbws8qOm",
		"domain": "facebook.com",
		"path": "/",
		"hostOnly": false,
		"creation": "2025-07-02T09:44:31.071Z",
		"lastAccessed": "2025-07-02T09:44:34.772Z"
	},
	{
		"key": "datr",
		"value": "nifmZn1JaTnpRkw_lgZ0ES0F",
		"domain": "facebook.com",
		"path": "/",
		"hostOnly": false,
		"creation": "2025-07-02T09:44:31.076Z",
		"lastAccessed": "2025-07-02T09:44:34.772Z"
	},
	{
		"key": "ps_l",
		"value": "1",
		"domain": "facebook.com",
		"path": "/",
		"hostOnly": false,
		"creation": "2025-07-02T09:44:31.077Z",
		"lastAccessed": "2025-07-02T09:44:34.772Z"
	},
	{
		"key": "ps_n",
		"value": "1",
		"domain": "facebook.com",
		"path": "/",
		"hostOnly": false,
		"creation": "2025-07-02T09:44:31.078Z",
		"lastAccessed": "2025-07-02T09:44:34.772Z"
	},
	{
		"key": "oo",
		"value": "v1",
		"domain": "facebook.com",
		"path": "/",
		"hostOnly": false,
		"creation": "2025-07-02T09:44:31.078Z",
		"lastAccessed": "2025-07-02T09:44:34.772Z"
	},
	{
		"key": "dpr",
		"value": "1.399999976158142",
		"domain": "facebook.com",
		"path": "/",
		"hostOnly": false,
		"creation": "2025-07-02T09:44:31.080Z",
		"lastAccessed": "2025-07-02T09:44:34.772Z"
	},
	{
		"key": "wd",
		"value": "1372x608",
		"domain": "facebook.com",
		"path": "/",
		"hostOnly": false,
		"creation": "2025-07-02T09:44:31.080Z",
		"lastAccessed": "2025-07-02T09:44:34.772Z"
	},
	{
		"key": "c_user",
		"value": "100058001108029",
		"domain": "facebook.com",
		"path": "/",
		"hostOnly": false,
		"creation": "2025-07-02T09:44:31.081Z",
		"lastAccessed": "2025-07-02T09:44:34.772Z"
	},
	{
		"key": "xs",
		"value": "12%3ANV2RzgZEPEmuqQ%3A2%3A1751247761%3A-1%3A-1%3A%3AAcVTpK6jChLhSxG9hJBrkl6CtXznqaoLYmKSDcm0NA",
		"domain": "facebook.com",
		"path": "/",
		"hostOnly": false,
		"creation": "2025-07-02T09:44:31.082Z",
		"lastAccessed": "2025-07-02T09:44:34.772Z"
	},
	{
		"key": "fr",
		"value": "1RP7xLNrzUSS5l1V7.AWdMPyPstB9Uax_QRfykEEJrMakX-oy4nFqcTV7il7EvJmo-ioM.BoZOzh..AAA.0.0.BoZP9_.AWdK1ZuWG0DSPyekXy4COMI_Hw0",
		"expires": "2025-09-30T09:44:31.000Z",
		"maxAge": 7776000,
		"domain": "facebook.com",
		"path": "/",
		"secure": true,
		"httpOnly": true,
		"extensions": [
			"SameSite=None"
		],
		"hostOnly": false,
		"creation": "2025-07-02T09:44:31.083Z",
		"lastAccessed": "2025-07-02T09:44:34.772Z"
	},
	{
		"key": "presence",
		"value": "C%7B%22t3%22%3A%5B%5D%2C%22utc3%22%3A1751446661144%2C%22v%22%3A1%7D",
		"domain": "facebook.com",
		"path": "/",
		"hostOnly": false,
		"creation": "2025-07-02T09:44:31.083Z",
		"lastAccessed": "2025-07-02T09:44:34.772Z"
	},
	{
		"key": "sb",
		"value": "nifmZsCEm1Wh5AfDjbws8qOm",
		"domain": "facebook.com",
		"path": "/",
		"hostOnly": false,
		"creation": "2025-07-02T09:44:31.071Z",
		"lastAccessed": "2025-07-02T09:44:34.772Z"
	},
	{
		"key": "datr",
		"value": "nifmZn1JaTnpRkw_lgZ0ES0F",
		"domain": "facebook.com",
		"path": "/",
		"hostOnly": false,
		"creation": "2025-07-02T09:44:31.076Z",
		"lastAccessed": "2025-07-02T09:44:34.772Z"
	},
	{
		"key": "ps_l",
		"value": "1",
		"domain": "facebook.com",
		"path": "/",
		"hostOnly": false,
		"creation": "2025-07-02T09:44:31.077Z",
		"lastAccessed": "2025-07-02T09:44:34.772Z"
	},
	{
		"key": "ps_n",
		"value": "1",
		"domain": "facebook.com",
		"path": "/",
		"hostOnly": false,
		"creation": "2025-07-02T09:44:31.078Z",
		"lastAccessed": "2025-07-02T09:44:34.772Z"
	},
	{
		"key": "oo",
		"value": "v1",
		"domain": "facebook.com",
		"path": "/",
		"hostOnly": false,
		"creation": "2025-07-02T09:44:31.078Z",
		"lastAccessed": "2025-07-02T09:44:34.772Z"
	},
	{
		"key": "dpr",
		"value": "1.399999976158142",
		"domain": "facebook.com",
		"path": "/",
		"hostOnly": false,
		"creation": "2025-07-02T09:44:31.080Z",
		"lastAccessed": "2025-07-02T09:44:34.772Z"
	},
	{
		"key": "wd",
		"value": "1372x608",
		"domain": "facebook.com",
		"path": "/",
		"hostOnly": false,
		"creation": "2025-07-02T09:44:31.080Z",
		"lastAccessed": "2025-07-02T09:44:34.772Z"
	},
	{
		"key": "c_user",
		"value": "100058001108029",
		"domain": "facebook.com",
		"path": "/",
		"hostOnly": false,
		"creation": "2025-07-02T09:44:31.081Z",
		"lastAccessed": "2025-07-02T09:44:34.772Z"
	},
	{
		"key": "xs",
		"value": "12%3ANV2RzgZEPEmuqQ%3A2%3A1751247761%3A-1%3A-1%3A%3AAcVTpK6jChLhSxG9hJBrkl6CtXznqaoLYmKSDcm0NA",
		"domain": "facebook.com",
		"path": "/",
		"hostOnly": false,
		"creation": "2025-07-02T09:44:31.082Z",
		"lastAccessed": "2025-07-02T09:44:34.772Z"
	},
	{
		"key": "fr",
		"value": "1RP7xLNrzUSS5l1V7.AWdMPyPstB9Uax_QRfykEEJrMakX-oy4nFqcTV7il7EvJmo-ioM.BoZOzh..AAA.0.0.BoZP9_.AWdK1ZuWG0DSPyekXy4COMI_Hw0",
		"expires": "2025-09-30T09:44:31.000Z",
		"maxAge": 7776000,
		"domain": "facebook.com",
		"path": "/",
		"secure": true,
		"httpOnly": true,
		"extensions": [
			"SameSite=None"
		],
		"hostOnly": false,
		"creation": "2025-07-02T09:44:31.083Z",
		"lastAccessed": "2025-07-02T09:44:34.772Z"
	},
	{
		"key": "presence",
		"value": "C%7B%22t3%22%3A%5B%5D%2C%22utc3%22%3A1751446661144%2C%22v%22%3A1%7D",
		"domain": "facebook.com",
		"path": "/",
		"hostOnly": false,
		"creation": "2025-07-02T09:44:31.083Z",
		"lastAccessed": "2025-07-02T09:44:34.772Z"
	},
	{
		"key": "fr",
		"value": "1RP7xLNrzUSS5l1V7.AWdMPyPstB9Uax_QRfykEEJrMakX-oy4nFqcTV7il7EvJmo-ioM.BoZOzh..AAA.0.0.BoZP9_.AWdK1ZuWG0DSPyekXy4COMI_Hw0",
		"expires": "2025-09-30T09:44:31.000Z",
		"maxAge": 7776000,
		"domain": "messenger.com",
		"path": "/",
		"secure": true,
		"httpOnly": true,
		"extensions": [
			"SameSite=None"
		],
		"hostOnly": false,
		"creation": "2025-07-02T09:44:31.091Z",
		"lastAccessed": "2025-07-02T09:44:34.772Z"
	}
]